MANIFEST.in
README
requirements.txt
setup.py
ajenti.plugin.filemanager.egg-info/PKG-INFO
ajenti.plugin.filemanager.egg-info/SOURCES.txt
ajenti.plugin.filemanager.egg-info/dependency_links.txt
ajenti.plugin.filemanager.egg-info/requires.txt
ajenti.plugin.filemanager.egg-info/top_level.txt
ajenti_plugin_filemanager/README.md
ajenti_plugin_filemanager/__init__.py
ajenti_plugin_filemanager/bower.json
ajenti_plugin_filemanager/main.py
ajenti_plugin_filemanager/plugin.yml
ajenti_plugin_filemanager/requirements.txt
ajenti_plugin_filemanager/locale/app.pot
ajenti_plugin_filemanager/locale/af/LC_MESSAGES/app.js
ajenti_plugin_filemanager/locale/af/LC_MESSAGES/app.po
ajenti_plugin_filemanager/locale/af/LC_MESSAGES/app.po~
ajenti_plugin_filemanager/locale/ar/LC_MESSAGES/app.js
ajenti_plugin_filemanager/locale/ar/LC_MESSAGES/app.po
ajenti_plugin_filemanager/locale/ar/LC_MESSAGES/app.po~
ajenti_plugin_filemanager/locale/be/LC_MESSAGES/app.js
ajenti_plugin_filemanager/locale/be/LC_MESSAGES/app.po
ajenti_plugin_filemanager/locale/be/LC_MESSAGES/app.po~
ajenti_plugin_filemanager/locale/bg/LC_MESSAGES/app.js
ajenti_plugin_filemanager/locale/bg/LC_MESSAGES/app.po
ajenti_plugin_filemanager/locale/bg/LC_MESSAGES/app.po~
ajenti_plugin_filemanager/locale/bn/LC_MESSAGES/app.js
ajenti_plugin_filemanager/locale/bn/LC_MESSAGES/app.po
ajenti_plugin_filemanager/locale/bn/LC_MESSAGES/app.po~
ajenti_plugin_filemanager/locale/bs/LC_MESSAGES/app.js
ajenti_plugin_filemanager/locale/bs/LC_MESSAGES/app.po
ajenti_plugin_filemanager/locale/ca/LC_MESSAGES/app.js
ajenti_plugin_filemanager/locale/ca/LC_MESSAGES/app.po
ajenti_plugin_filemanager/locale/ca/LC_MESSAGES/app.po~
ajenti_plugin_filemanager/locale/cs/LC_MESSAGES/app.js
ajenti_plugin_filemanager/locale/cs/LC_MESSAGES/app.po
ajenti_plugin_filemanager/locale/cs/LC_MESSAGES/app.po~
ajenti_plugin_filemanager/locale/da/LC_MESSAGES/app.js
ajenti_plugin_filemanager/locale/da/LC_MESSAGES/app.po
ajenti_plugin_filemanager/locale/da/LC_MESSAGES/app.po~
ajenti_plugin_filemanager/locale/de/LC_MESSAGES/app.js
ajenti_plugin_filemanager/locale/de/LC_MESSAGES/app.po
ajenti_plugin_filemanager/locale/de/LC_MESSAGES/app.po~
ajenti_plugin_filemanager/locale/el/LC_MESSAGES/app.js
