Metadata-Version: 1.2
Name: ajenti.plugin.filemanager
Version: 0.30
Summary: File Manager
Home-page: https://ajenti.org
Author: Ajenti project
Author-email: e@ajenti.org
License: UNKNOWN
Platform: UNKNOWN
Requires-Python: >=3
